Workbook

Sheet Portada
B4: Resolución 5018 de 2019
B5: por la cual se establecen lineamientos en Seguridad y Salud en el trabajo en los Procesos de Generación, Transmisión, Distribución y Comercialización de la Energía Eléctrica.
C8: Nombre de la empresa:
C9: Nit de la empresa:
C10: Centro de trabajo al que le aplican la línea basal:
C11: Fecha de realización:
C12: Realizado por:
C13: Cargo:
C14: Asesorado por:
C15: Cargo:
C16: Ciudad:
C17: Departamento de ubicación:
C18: Sector económico:
C19: Clase de riesgo:
B20: “Todos los derechos reservados. El presente documento, su diseño y contenido es para uso exclusivo de los usuarios/clientes de SURA, quienes se encuentran facultados para ajustarlo y modificarlo teniendo en cuenta sus necesidades y particularidades con el fin de cumplir sus obligaciones, razón por la cual se encuentra prohibido cualquier uso diferente, así como su comercialización, reproducción y transmisión sin el permiso previo y escrito de SURA. © Propiedad Intelectual de Seguros de Vida Suramericana S.A., ARL SURA, marzo de 2021”.

Sheet Siglas
A2: Seguros de Vida Suramericana S.A., ARL SURA. © Copyright – Marzo de 2021. Todos los derechos reservados.
A5: SIGLA | B5: DEFINICIÓN
A6: NFPA | B6: NATIONAL FIRE PROTECTION ASSOCIATION
A7: RETIE | B7: REGLAMENTO TÉCNICO DE INSTALACIONES ELÉCTRICAS
A8: SG - SST | B8: SISTEMA DE GESTIÓN EN SEGURIDAD Y SALUD E EL TRABAJO
A9: SENA | B9: SERVICIO NACIONAL DE APRENDIZAJE

Sheet SST sector EL. y Actividades
A5: Seguros de Vida Suramericana S.A., ARL SURA. © Copyright – Marzo de 2021. Todos los derechos reservados.
A6: Resolución 5018 de 2019
A7: N° | B7: ITEM | C7: SST SECTOR ELECTRICO Y ACTIVIDADES RELACIONADAS- Generalidades | I7: Calificación | J7: Puntaje
A8: 1 | B8: Generalidades | C8: Se tiene identificada en la matriz de requisitos la legislación referente a la resolución 6045 del 2014 del Ministerio del Trabajo; LA Resolución 3710 de 2019 del Ministerio de Trabajo, el Decreto Único Reglamentario 1072 de 2015 del Sector Trabajo, en los artículos 2.2.4.6.1, 2.2.4.6.8, el articulo 348 del Código Sustantivo del Trabajo, y el articulo 84 de Ia Ley 9 de 1979? | I8: Cumple totalmente | J8: =IF(I8="No cumple",0,IF(I8="No aplica",2,IF(I8="Cumple totalmente",2,IF(I8="Cumple parcialmente",1)))) -> 2
A9: 2 | B9: Generalidades | C9: Se tiene identificada la Resolución 5018/19 en la matriz de requisitos legales? | I9: No cumple | J9: =IF(I9="No cumple",0,IF(I9="No aplica",2,IF(I9="Cumple totalmente",2,IF(I9="Cumple parcialmente",1)))) -> 0
A10: 3 | B10: Artículo 1 | C10: Se cuenta con Programa para Control del Peligro Eléctrico? | I10: No cumple | J10: =IF(I10="No cumple",0,IF(I10="No aplica",2,IF(I10="Cumple totalmente",2,IF(I10="Cumple parcialmente",1)))) -> 0
A11: 4 | B11: Artículo 1 | C11: Se cuenta con hojas de vida del personal externo que realiza actividades en seguridad y salud en el trabajo? | I11: No aplica | J11: =IF(I11="No cumple",0,IF(I11="No aplica",2,IF(I11="Cumple totalmente",2,IF(I11="Cumple parcialmente",1)))) -> 2
A12: 5 | B12: Artículo 1 | C12: La organización cuenta con procedimientos de perfiles de cargo y se validan las hojas de vida del personal técnico y de seguridad? | I12: Cumple totalmente | J12: =IF(I12="No cumple",0,IF(I12="No aplica",2,IF(I12="Cumple totalmente",2,IF(I12="Cumple parcialmente",1)))) -> 2
A13: 6 | B13: Artículo 2 | C13: La organización cuenta con el procedimiento de habilitación y se encuentra evidenciada la habilitación del personal ? | I13: No cumple | J13: =IF(I13="No cumple",0,IF(I13="No aplica",2,IF(I13="Cumple totalmente",2,IF(I13="Cumple parcialmente",1)))) -> 0
A14: 7 | B14: Artículo 2 | C14: Se realiza formación en Riesgo eléctrico a todo el personal operativo y administrativo? | I14: No cumple | J14: =IF(I14="No cumple",0,IF(I14="No aplica",2,IF(I14="Cumple totalmente",2,IF(I14="Cumple parcialmente",1)))) -> 0
A15: 8 | B15: Artículo 2 | C15: Se cuenta con la autorización para acceder y manipular instalaciones eléctricas? | I15: Cumple parcialmente | J15: =IF(I15="No cumple",0,IF(I15="No aplica",2,IF(I15="Cumple totalmente",2,IF(I15="Cumple parcialmente",1)))) -> 1
A16: 9 | B16: Artículo 3 | C16: Se realiza charla pre operativa en donde se identifiquen responsables, peligros, actividades, niveles de tensión y procedimientos de operación entre otros? | I16: Cumple totalmente | J16: =IF(I16="No cumple",0,IF(I16="No aplica",2,IF(I16="Cumple totalmente",2,IF(I16="Cumple parcialmente",1)))) -> 2
A17: 10 | B17: Artículo 3 | C17: Se cuenta con los equipos y herramientas adecuados para realizar actividades eléctricas según el método de ejecución? | I17: Cumple totalmente | J17: =IF(I17="No cumple",0,IF(I17="No aplica",2,IF(I17="Cumple totalmente",2,IF(I17="Cumple parcialmente",1)))) -> 2
A18: 11 | B18: Artículo 3 | C18: La empresa cuenta con un protocolo de comunicaciones propio o del contratante para mantener la comunicación permanente entre equipos de trabajo y centros de control? | I18: Cumple totalmente | J18: =IF(I18="No cumple",0,IF(I18="No aplica",2,IF(I18="Cumple totalmente",2,IF(I18="Cumple parcialmente",1)))) -> 2
A19: 12 | B19: Artículo 3 | C19: La organización cuenta con un protocolo de comunicaciones interna para manejo de emergencias? | I19: Cumple totalmente | J19: =IF(I19="No cumple",0,IF(I19="No aplica",2,IF(I19="Cumple totalmente",2,IF(I19="Cumple parcialmente",1)))) -> 2
... A39: 32 | B39: Artículo 10 | C39: La organización cuenta con Plan (permiso, descargo, autorización, incidencia) de trabajo para intervenciones eléctricas y se realiza diagnóstico previo para determinar actividades, tiempo y método de trabajo? | I39: Cumple parcialmente | J39: =IF(I39="No cumple",0,IF(I39="No aplica",2,IF(I39="Cumple totalmente",2,IF(I39="Cumple parcialmente",1)))) -> 1
A40: 33 | B40: Artículo 10 | C40: Se realizan las actividades previas a la operación como la reunión pre operativa, se identifican peligros y se realiza el diligenciamiento de los registros por parte del líder ? | I40: Cumple parcialmente | J40: =IF(I40="No cumple",0,IF(I40="No aplica",2,IF(I40="Cumple totalmente",2,IF(I40="Cumple parcialmente",1)))) -> 1 | K40: PUNTAJE OBTENIDO | L40: PUNTAJE MAXIMO | M40: PORCENTAJE
A41: N° | B41: ITEM | C41: SST SECTOR ELECTRICO Y ACTIVIDADES RELACIONADAS- Distancias de seguridad | I41: Calificación | J41: Puntaje | K41: =SUM(J8:J40) -> 38 | L41: 66 | M41: =(K41*100/66)% -> 0.57575758
A42: 1 | B42: Artículo 11 | C42: En la operación se garantiza el cumplimento de las distancias de seguridad a que se refiere el RETIE? | I42: Cumple parcialmente | J42: =IF(I42="No cumple",0,IF(I42="No aplica",2,IF(I42="Cumple totalmente",2,IF(I42="Cumple parcialmente",1)))) -> 1
A43: 2 | B43: Artículo 12 | C43: La organización cuenta con procedimiento para señalización e identificación de fases y estas se encuentran señalizadas e identificadas? | I43: Cumple parcialmente | J43: =IF(I43="No cumple",0,IF(I43="No aplica",2,IF(I43="Cumple totalmente",2,IF(I43="Cumple parcialmente",1)))) -> 1 | K43: PUNTAJE OBTENIDO | L43: PUNTAJE MAXIMO | M43: PORCENTAJE
A44: N° | B44: ITEM | C44: SST SECTOR ELECTRICO Y ACTIVIDADES RELACIONADAS-Transformacion | I44: Calificación | J44: Puntaje | K44: 2 | L44: 4 | M44: =(K44*100/4)% -> 0.5
A45: 1 | B45: Artículo 13 | C45: Para las actividades del proceso de transformación la organización cuenta con procedimientos para la ejecución de Ordenes de Trabajo para el mantenimiento y la operación de todos los equipos.? | I45: Cumple totalmente | J45: =IF(I45="No cumple",0,IF(I45="No aplica",2,IF(I45="Cumple totalmente",2,IF(I45="Cumple parcialmente",1)))) -> 2
A46: 2 | B46: Artículo 13 | C46: Se realiza entrega y devolución de los equipos en la condición operativa indicada en el plan de trabajo aprobado por parte del responsable? | I46: No cumple | J46: =IF(I46="No cumple",0,IF(I46="No aplica",2,IF(I46="Cumple totalmente",2,IF(I46="Cumple parcialmente",1)))) -> 0
A47: 3 | B47: Artículo 13 | C47: Se Dispone de una copia actualizada de los procedimientos de operación de equipos de la Subestación dentro de la instalación, tanto en condiciones normales como de emergencia, incluyendo los pianos eléctricos actualizados correspondientes y los manuales de operación.? | I47: Cumple parcialmente | J47: =IF(I47="No cumple",0,IF(I47="No aplica",2,IF(I47="Cumple totalmente",2,IF(I47="Cumple parcialmente",1)))) -> 1
A48: 4 | B48: Artículo 13 | C48: Los equipos se encuentran plenamente identificados y rotulados para realizar cualquier operación y/o mantenimiento.? | I48: Cumple totalmente | J48: =IF(I48="No cumple",0,IF(I48="No aplica",2,IF(I48="Cumple totalmente",2,IF(I48="Cumple parcialmente",1)))) -> 2
A49: 5 | B49: Artículo 13 | C49: La organización garantiza que el personal no porta dentro de la Subestación elementos metálicos que pongan en riesgo su vida o la de sus acompañantes.? | I49: Cumple totalmente | J49: =IF(I49="No cumple",0,IF(I49="No aplica",2,IF(I49="Cumple totalmente",2,IF(I49="Cumple parcialmente",1)))) -> 2
A50: 6 | B50: Artículo 13 | C50: El personal asignado al desarrollo de actividades complementarias en subestaciones eléctricas, tales como la vigilancia, obras civiles, mantenimiento, aseo, entre otras, recibe acción sobre los peligros y riesgos eléctricos a los cuales estará expuesto en esa instalación, y cuenta con la autorización para su ingreso y la necesidad de la supervisión de los trabajos, si lo requiere, por parte del responsable de validar el cumplimiento de los demás requisitos legales y contractuales.? | I50: No cumple | J50: =IF(I50="No cumple",0,IF(I50="No aplica",2,IF(I50="Cumple totalmente",2,IF(I50="Cumple parcialmente",1)))) -> 0
A51: 7 | B51: Artículo 14 | C51: Las Subestaciones de patio se encuentran recubiertas con una capa de gravilla como medida de protección eléctrica y para permitir que se extinga cualquier incendio ocasionado per derrame de aceite.? | I51: Cumple totalmente | J51: =IF(I51="No cumple",0,IF(I51="No aplica",2,IF(I51="Cumple totalmente",2,IF(I51="Cumple parcialmente",1)))) -> 2
A52: 8 | B52: Artículo 14 | C52: En las subestaciones de patio se mantienen en funcionamiento los drenajes que eviten la acumulación de agua en los patios. Los cárcamos y registros deben contar todos con sus respectivas tapas, en buen estado y puestas en su lugar | I52: Cumple totalmente | J52: =IF(I52="No cumple",0,IF(I52="No aplica",2,IF(I52="Cumple totalmente",2,IF(I52="Cumple parcialmente",1)))) -> 2
A53: 9 | B53: Artículo 14 | C53: Las cercas, mampostería, alambrados y mallas de encerramiento deben estar en buenas condiciones y debidamente conectadas a tierra? | I53: Cumple totalmente | J53: =IF(I53="No cumple",0,IF(I53="No aplica",2,IF(I53="Cumple totalmente",2,IF(I53="Cumple parcialmente",1)))) -> 2
A54: 10 | B54: Artículo 14 | C54: Se realiza el control periódico de plagas, roedores y vegetación, mediante controles químicos o biológicos aplicando la legislación vigente en materia ambiental y de seguridad y salud en el trabajo.? | I54: Cumple totalmente | J54: =IF(I54="No cumple",0,IF(I54="No aplica",2,IF(I54="Cumple totalmente",2,IF(I54="Cumple parcialmente",1)))) -> 2
A55: 11 | B55: Artículo 14 | C55: En ejecución de maniobras en subestaciones siempre se cuenta con un medio de comunicación entre el personal habilitado y centro de control.? | I55: Cumple totalmente | J55: =IF(I55="No cumple",0,IF(I55="No aplica",2,IF(I55="Cumple totalmente",2,IF(I55="Cumple parcialmente",1)))) -> 2
A56: 12 | B56: Artículo 14 | C56: Al retiro de cubiertas, protecciones o frentes muertos de las partes energizadas de los tableros, se delimita el área de trabajo con barreras de seguridad y avisos de peligro, ? | I56: Cumple parcialmente | J56: =IF(I56="No cumple",0,IF(I56="No aplica",2,IF(I56="Cumple totalmente",2,IF(I56="Cumple parcialmente",1)))) -> 1
... A86: 42 | B86: Artículo 21 | C86: En la realización de pruebas de inyección de corriente se confirma que los caminos de corriente se encuentren cerrados (continuidad del circuito) y se Utilizar las puntas de prueba adecuadas y en buen estado; se asegura que los cables no se soltaran en Ia ejecución de la misma.. ? | I86: No aplica | J86: =IF(I86="No cumple",0,IF(I86="No aplica",2,IF(I86="Cumple totalmente",2,IF(I86="Cumple parcialmente",1)))) -> 2
A87: 43 | B87: Artículo 22 | C87: En cámaras de registro y cárcamos se evidencia que no se encuentren inundados y se inspecciona y hace mantenimiento periódico a los drenajes.? | I87: Cumple totalmente | J87: =IF(I87="No cumple",0,IF(I87="No aplica",2,IF(I87="Cumple totalmente",2,IF(I87="Cumple parcialmente",1)))) -> 2 | K87: PUNTAJE OBTENIDO | L87: PUNTAJE MAXIMO | M87: PORCENTAJE
A88: 44 | B88: Artículo 22 | C88: Se realiza el análisis y control de peligros y se aplican los controles necesarios con los conductores energizados; igualmente evaluar y controlar otros posibles peligros (trabajo en alturas, espacios confinados, riesgo biológico, entre otros).? | I88: Cumple totalmente | J88: =IF(I88="No cumple",0,IF(I88="No aplica",2,IF(I88="Cumple totalmente",2,IF(I88="Cumple parcialmente",1)))) -> 2 | K88: =SUM(J45:J88) -> 80 | L88: 88 | M88: =(K88*100/88)% -> 0.90909091
A89: N° | B89: ITEM | C89: SST SECTOR ELECTRICO Y ACTIVIDADES RELACIONADAS-Areas de trabajo | I89: Calificación | J89: Puntaje
A90: 1 | B90: Artículo 23 | C90: Los talleres de mantenimiento cuentan con amplitud, iluminación, ventilación y se encuentran en óptimas Condiciones de orden y aseo, cuentan con equipos para el control de incendios y existe señalización y demarcación. los equipos cuentas con guardas protectoras en los equipos que lo requieran.? | I90: Cumple totalmente | J90: =IF(I90="No cumple",0,IF(I90="No aplica",2,IF(I90="Cumple totalmente",2,IF(I90="Cumple parcialmente",1)))) -> 2
A91: 2 | B91: Artículo 24 | C91: Los laboratorios cuentan con amplitud, iluminación, ventilación y se encuentran en óptimas Condiciones de orden y aseo, cuentan con equipos para el control de incendios y existe señalización y demarcación. los equipos cuentan con guardas protectoras y se realiza la certificación de calibración de los equipos.? | I91: Cumple totalmente | J91: =IF(I91="No cumple",0,IF(I91="No aplica",2,IF(I91="Cumple totalmente",2,IF(I91="Cumple parcialmente",1)))) -> 2
A92: 3 | B92: Artículo 25 | C92: En instalaciones y áreas restringidas se establecen procedimientos que regulen el comportamiento de los trabajadores, así como de las personas advertidas, dentro de sus instalaciones.? | I92: Cumple totalmente | J92: =IF(I92="No cumple",0,IF(I92="No aplica",2,IF(I92="Cumple totalmente",2,IF(I92="Cumple parcialmente",1)))) -> 2
A93: 4 | B93: Artículo 25 | C93: Las áreas restringidas se encuentran plenamente identificadas y señalizadas y el ingreso a las mismas es autorizado por la empresa.? | I93: Cumple totalmente | J93: =IF(I93="No cumple",0,IF(I93="No aplica",2,IF(I93="Cumple totalmente",2,IF(I93="Cumple parcialmente",1)))) -> 2
A94: 5 | B94: Artículo 25 | C94: La instalaciones y áreas restringidas cuentan con senderos de circulación y su sentido de tránsito cuando el análisis de riesgos y las necesidades de su control lo requieran.? | I94: Cumple parcialmente | J94: =IF(I94="No cumple",0,IF(I94="No aplica",2,IF(I94="Cumple totalmente",2,IF(I94="Cumple parcialmente",1)))) -> 1
A95: 6 | B95: Artículo 25 | C95: Las vías de circulación de peatones y vehículos dentro de las instalaciones se encuentran completamente despejadas y cuentan con Ia iluminación requerida para su circulación.? | I95: No aplica | J95: =IF(I95="No cumple",0,IF(I95="No aplica",2,IF(I95="Cumple totalmente",2,IF(I95="Cumple parcialmente",1)))) -> 2
A96: 7 | B96: Artículo 25 | C96: En el evento de realizarse trabajos en dichas vías, presentarse derrames de sustancias, realizar actividades de cargue y descargue, se señaliza y demarca el área afectada, de manera que sea plenamente observable tanto de día como de noche.? | I96: Cumple totalmente | J96: =IF(I96="No cumple",0,IF(I96="No aplica",2,IF(I96="Cumple totalmente",2,IF(I96="Cumple parcialmente",1)))) -> 2
A97: 8 | B97: Artículo 25 | C97: Las instalaciones, deben cuentan con programa de mantenimiento, con el propósito de evitar su deterioro y, por ende, la ocurrencia de accidentes en el personal que las habite ocupe o visite acorde al RETIE? | I97: Cumple totalmente | J97: =IF(I97="No cumple",0,IF(I97="No aplica",2,IF(I97="Cumple totalmente",2,IF(I97="Cumple parcialmente",1)))) -> 2
A98: 9 | B98: Artículo 26 | C98: El personal No electricista cuenta con formación y/o capacitación en peligros eléctricos, identificación de peligros y cuentan con elementos de protección personal.? | I98: No cumple | J98: =IF(I98="No cumple",0,IF(I98="No aplica",2,IF(I98="Cumple totalmente",2,IF(I98="Cumple parcialmente",1)))) -> 0
A99: 10 | B99: Artículo 26 | C99: Se cuenta con personal habilitado que ejerza supervisión constante? | I99: No cumple | J99: =IF(I99="No cumple",0,IF(I99="No aplica",2,IF(I99="Cumple totalmente",2,IF(I99="Cumple parcialmente",1)))) -> 0 | K99: PUNTAJE OBTENIDO | L99: PUNTAJE MAXIMO | M99: PORCENTAJE
A100: 11 | B100: Artículo 26 | C100: Los andamios se encuentran aterrizados y el traslado de varillas, niveles, equipos de topografía y cualquier elemento metálico se realiza a menos altura del que la transporta? | I100: Cumple totalmente | J100: =IF(I100="No cumple",0,IF(I100="No aplica",2,IF(I100="Cumple totalmente",2,IF(I100="Cumple parcialmente",1)))) -> 2 | K100: =SUM(J90:J100) -> 17 | L100: 22 | M100: =(K100*100/22)% -> 0.77272727
A101: N° | B101: ITEM | C101: SST SECTOR ELECTRICO Y ACTIVIDADES RELACIONADAS-Atencion de Emergencias | I101: Calificación | J101: Puntaje
A102: 1 | B102: Artículo 27 | C102: El plan de atención de emergencias se encuentra actualizado y se actualiza el análisis de vulnerabilidad cada año, se incluyen las valoraciones de emergencia eléctrica acorde a las actividades misionales de la empresa | I102: No cumple | J102: =IF(I102="No cumple",0,IF(I102="No aplica",2,IF(I102="Cumple totalmente",2,IF(I102="Cumple parcialmente",1)))) -> 0
A103: 2 | B103: Artículo 27 | C103: El plan de emergencias cuenta con los recursos para su atención como sistemas de detección, notificación y alarmas, Brigadas de atención y de rescate, Atención a lesionados, grupos de apoyo externo, El personal se encuentra informado sobre Ia inhabilitación de los sistemas cuando así ocurriese, se documentan los procedimientos operativos normalizados de actuación para las vulnerabilidades eléctricas priorizadas, se establecen anualmente ensayos y pruebas de las medidas planificadas (Planes de emergencia) para la atención de las emergencias eléctricas y se cuenta con medios de comunicación.? | I103: No cumple | J103: =IF(I103="No cumple",0,IF(I103="No aplica",2,IF(I103="Cumple totalmente",2,IF(I103="Cumple parcialmente",1)))) -> 0
A104: 3 | B104: Artículo 28 | C104: Se referencian las buenas practicas para determinar e implementar las mejores formas de proteger las subestaciones contra incendios? | I104: No aplica | J104: =IF(I104="No cumple",0,IF(I104="No aplica",2,IF(I104="Cumple totalmente",2,IF(I104="Cumple parcialmente",1)))) -> 2 | K104: PUNTAJE OBTENIDO | L104: PUNTAJE MAXIMO | M104: PORCENTAJE
A105: N° | B105: ITEM | C105: SST SECTOR ELECTRICO Y ACTIVIDADES RELACIONADAS-Transporte | I105: Calificación | J105: Puntaje | K105: 2 | L105: 6 | M105: =(K105*100/6)% -> 0.33333333
A106: NO APLICA
A107: N° | B107: ITEM | C107: SST SECTOR ELECTRICO Y ACTIVIDADES RELACIONADAS- Trabajo en alturas | I107: Calificación | J107: Puntaje
A108: 1 | B108: Artículo 31 | C108: Se da cumplimiento a la legislación nacional e internacional para realizar trabajos en alturas y se establecen los procedimientos aplicables según las características del proceso y previo análisis de peligros.? | I108: Cumple totalmente | J108: =IF(I108="No cumple",0,IF(I108="No aplica",2,IF(I108="Cumple totalmente",2,IF(I108="Cumple parcialmente",1)))) -> 2
A109: 2 | B109: Artículo 31 | C109: Para el trabajo en alturas con exposición a peligros eléctricos el uso de escaleras portables, cumplen con las normas técnicas y de seguridad correspondiente y están compuestas de material en fibra de vidrio.? | I109: Cumple totalmente | J109: =IF(I109="No cumple",0,IF(I109="No aplica",2,IF(I109="Cumple totalmente",2,IF(I109="Cumple parcialmente",1)))) -> 2
A110: 3 | B110: Artículo 31 | C110: Se realiza el mantenimiento y certificación de las escaleras; en caso de daño o que se encuentre insegura se realiza el retiro y se almacena debidamente marcada mientras se realiza su disposición final o reparación.? | I110: Cumple totalmente | J110: =IF(I110="No cumple",0,IF(I110="No aplica",2,IF(I110="Cumple totalmente",2,IF(I110="Cumple parcialmente",1)))) -> 2
A111: 4 | B111: Artículo 31 | C111: En el uso de escaleras fijas (peldaños), se cumplen consideraciones: a) No se deben utilizar llevando objetos que ocupen las dos manos o que impidan la visibilidad. b) Deben estar limpias y sin obstrucciones. c) Deben estar secas, en buen estado y con materiales antideslizantes. d) Deben estar provistas de pasamanos. | I111: Cumple totalmente | J111: =IF(I111="No cumple",0,IF(I111="No aplica",2,IF(I111="Cumple totalmente",2,IF(I111="Cumple parcialmente",1)))) -> 2 | K111: PUNTAJE OBTENIDO | L111: PUNTAJE MAXIMO | M111: PORCENTAJE
A112: N° | B112: ITEM | C112: SST SECTOR ELECTRICO Y ACTIVIDADES RELACIONADAS- Elementos de protección individual, colectiva y herramientas de seguridad | I112: Calificación | J112: Puntaje | K112: 8 | L112: 8 | M112: =(K112*100/8)% -> 1
A113: 1 | B113: Artículo 32 | C113: La organización suministra oportunamente a sus trabajadores y de conformidad a Ia labor, elementos y equipos de seguridad, requerido para la ejecución de los trabajos y realiza Ia reposición de los mismos cuando por su deterioro o pérdida sea requerido? | I113: Cumple totalmente | J113: =IF(I113="No cumple",0,IF(I113="No aplica",2,IF(I113="Cumple totalmente",2,IF(I113="Cumple parcialmente",1)))) -> 2
A114: 2 | B114: Artículo 32 | C114: La ropa de labor para el personal está confeccionada en algodón para categoría cero, sin accesorios metálicos.? | I114: No cumple | J114: =IF(I114="No cumple",0,IF(I114="No aplica",2,IF(I114="Cumple totalmente",2,IF(I114="Cumple parcialmente",1)))) -> 0
A115: 3 | B115: Artículo 32 | C115: La organización, apoyada en normas técnicas, realiza un análisis de riesgos para exposición a arco eléctrico acorde al nivel de tensión para cada uno de sus procesos y tiene definido el tipo de protección especial se requiere considerando la exposición a corrientes de cortocircuito en las condiciones mas desfavorables para cada caso.? | I115: No cumple | J115: =IF(I115="No cumple",0,IF(I115="No aplica",2,IF(I115="Cumple totalmente",2,IF(I115="Cumple parcialmente",1)))) -> 0
A116: 4 | B116: Artículo 32 | C116: La ropa y/o indumentaria de protección contra arco eléctrico esta diseñada conforme con la categoría Peligro/Riesgo establecida en la NFPA 70E, y los estudios de peligro de arco eléctrico realizados con el mismo propósito.? | I116: No cumple | J116: =IF(I116="No cumple",0,IF(I116="No aplica",2,IF(I116="Cumple totalmente",2,IF(I116="Cumple parcialmente",1)))) -> 0
A117: 5 | B117: Artículo 32 | C117: La organización tiene establecida la formación y capacitación acorde a la normatividad legal vigente a los trabajadores sabre el uso, mantenimiento, inspección y almacenamiento de los elementos y equipos de Protección Personal y colectivos indicando las características técnicas, como utilizarlos, cuidados y criterios de reposición.? | I117: Cumple parcialmente | J117: =IF(I117="No cumple",0,IF(I117="No aplica",2,IF(I117="Cumple totalmente",2,IF(I117="Cumple parcialmente",1)))) -> 1
A118: 6 | B118: Artículo 32 | C118: La organización realiza control diario a fin de garantizar que los trabajadores antes del inicio de actividades, realice la revisión y el uso adecuado de los elementos y equipo de protección requerido de acuerdo a los factores de riesgo a los cuales va a estar expuesto y la organización tiene implementado un programa de inspección de los elementos y equipos de protección personal y colectivos.? | I118: No cumple | J118: =IF(I118="No cumple",0,IF(I118="No aplica",2,IF(I118="Cumple totalmente",2,IF(I118="Cumple parcialmente",1)))) -> 0 | K118: PUNTAJE OBTENIDO | L118: PUNTAJE MAXIMO | M118: PORCENTAJE
A119: 7 | B119: Artículo 32 | C119: La organización dispone con un Kit de Bloqueo, Etiquetado y Condenación de acuerdo con los sistemas existentes y con la posibilidad de liberación de energías peligrosas.? | I119: Cumple totalmente | J119: =IF(I119="No cumple",0,IF(I119="No aplica",2,IF(I119="Cumple totalmente",2,IF(I119="Cumple parcialmente",1)))) -> 2 | K119: 5 | L119: 14 | M119: =(K119*100/14)% -> 0.35714286
A120: N° | B120: ITEM | C120: SST SECTOR ELECTRICO Y ACTIVIDADES RELACIONADAS- Disposiciones para la habilitación del personal en desarrollo de la actividad laboral en el sector eléctrico | I120: Calificación | J120: Puntaje
A121: 1 | B121: Artículo 33 | C121: La organización tiene establecido un procedimiento de habilitación para el personal que realiza labores con exposición a peligro eléctrico, se encuentra documentado y como mínimo contempla los componentes de formación, experiencia, capacitación y entrenamiento; incluye la certificación de las Normas de Competencia Laboral vigentes según el alcance de las mismas. Igualmente, el proceso de habilitación contempla, en casos específicos, la obligación de acompañamiento activo par parte de personal habilitado, para los trabajadores que cambian de oficio o se reincorporen después de ausencias prolongadas de su actividad operativa.? | I121: No cumple | J121: =IF(I121="No cumple",0,IF(I121="No aplica",2,IF(I121="Cumple totalmente",2,IF(I121="Cumple parcialmente",1)))) -> 0
A122: 2 | B122: Artículo 33 | C122: La organización tiene establecidas las actividades de formación, capacitación y entrenamiento en asuntos de Seguridad y Salud en el Trabajo (SST), de acuerdo a la normatividad legal vigente, se encuentran establecidas en el plan de trabajo anual como parte del SG-SST y cumplen con la intensidad horaria suficiente para abarcar los riesgos específicos según la exposición a los peligros debidos al cargo, labor, actividad o proceso; cada programa podrá desarrollarse en sesiones cuya duración mínima debe ser de dos horas, La organización garantiza la formación a todos los niveles jerárquicos que estén comprometidos en el proceso productivo (planeación, programación, ejecución y control) y los registros hacen referencia a los contenidos específicos desarrollados en la misma.? | I122: No cumple | J122: =IF(I122="No cumple",0,IF(I122="No aplica",2,IF(I122="Cumple totalmente",2,IF(I122="Cumple parcialmente",1)))) -> 0
A123: 3 | B123: Artículo 33 | C123: La organización cuenta o tiene establecido ejecutar los programas de formación, capacitación y entrenamiento, con Unidades Vocacionales de Aprendizaje Empresarial. | I123: No aplica | J123: =IF(I123="No cumple",0,IF(I123="No aplica",2,IF(I123="Cumple totalmente",2,IF(I123="Cumple parcialmente",1)))) -> 2
A124: 4 | B124: Artículo 33 | C124: La organización realiza la certificación de competencias laborales y esta es expedida por escrito, por el Servicio Nacional de Aprendizaje (SENA), o cualquier otro organismo de certificación de competencias laborales acreditado legalmente para el efecto.? | I124: No cumple | J124: =IF(I124="No cumple",0,IF(I124="No aplica",2,IF(I124="Cumple totalmente",2,IF(I124="Cumple parcialmente",1)))) -> 0
A125: 5 | B125: Artículo 34 | C125: La organización en desarrollo de las actividades realiza poda, mantenimiento de vegetación o alguna actividad silvicultural.? | I125: Cumple totalmente | J125: =IF(I125="No cumple",0,IF(I125="No aplica",2,IF(I125="Cumple totalmente",2,IF(I125="Cumple parcialmente",1)))) -> 2
A126: 6 | B126: Artículo 34 | C126: La organización realiza la validación de los permisos de la autoridad ambiental y verificar el buen estado de los equipos de ascenso, cuerdas y herramientas de corte.? | I126: Cumple totalmente | J126: =IF(I126="No cumple",0,IF(I126="No aplica",2,IF(I126="Cumple totalmente",2,IF(I126="Cumple parcialmente",1)))) -> 2
A127: 7 | B127: Artículo 34 | C127: Las actividades silviculturales en las que se interviene redes energizadas se contemplaran los requisitos de trabajos con tensión, así mismo se consideran energizados los circuitos cuyos conductores sean semi aislados, cubiertos, protegidos o ecológicos.? | I127: Cumple totalmente | J127: =IF(I127="No cumple",0,IF(I127="No aplica",2,IF(I127="Cumple totalmente",2,IF(I127="Cumple parcialmente",1)))) -> 2
A128: 8 | B128: Artículo 34 | C128: El personal que realizar la poda técnica cuenta con la habilitación de Ia empresa y esta formado en peligros eléctricos.? Para las trabajos de poda donde se intervengan en redes desenergizadas se deben aplicar las Reglas de Oro y los procedimientos seguros de trabajo para la intervención del peligro eléctrico. | I128: Cumple totalmente | J128: =IF(I128="No cumple",0,IF(I128="No aplica",2,IF(I128="Cumple totalmente",2,IF(I128="Cumple parcialmente",1)))) -> 2 | K128: PUNTAJE OBTENIDO | L128: PUNTAJE MAXIMO | M128: PORCENTAJE
A129: 9 | B129: Artículo 34 | C129: Para las trabajos de poda donde se intervienen desenergizadas la organización realiza la aplicación de las 5 Reglas de Oro y establece los procedimientos seguros de trabajo para la intervención del peligro eléctrico.? | I129: Cumple totalmente | J129: =IF(I129="No cumple",0,IF(I129="No aplica",2,IF(I129="Cumple totalmente",2,IF(I129="Cumple parcialmente",1)))) -> 2 | K129: 12 | L129: 18 | M129: =(K129*100/18)% -> 0.66666667
M134: =+A129+A119+A111+A104+A100+A88+A43+A40 -> 113
M135: =113*2 -> 226

Sheet Centrales Térmicas
A2: Seguros de Vida Suramericana S.A., ARL SURA. © Copyright – Marzo de 2021. Todos los derechos reservados.
A6: Resolución 5018 de 2019
A7: N° | B7: ITEM | C7: CENTRAL TERMICA- Generalidades | I7: Calificación | J7: Puntaje
A8: 1 | B8: Artículo 35 - a | C8: ¿Las partes de maquinaria que se encuentren en movimiento permanecen protegidas? o ¿se cuenta con los métodos de control en el medio y distancias de seguridad? | J8: =IF(I8="No cumple",0,IF(I8="No aplica",2,IF(I8="Cumple totalmente",2,IF(I8="Cumple parcialmente",1)))) -> FALSE
A9: 2 | B9: Artículo 35 - b | C9: ¿Las tuberías y equipos cumple con el código de colores? | J9: =IF(I9="No cumple",0,IF(I9="No aplica",2,IF(I9="Cumple totalmente",2,IF(I9="Cumple parcialmente",1)))) -> FALSE
A10: 3 | B10: Artículo 35 - c | C10: ¿Las carátulas y ventanillas de los instrumentos indicadores o controladores se encuentran limpias y en buen estado? | J10: =IF(I10="No cumple",0,IF(I10="No aplica",2,IF(I10="Cumple totalmente",2,IF(I10="Cumple parcialmente",1)))) -> FALSE
A11: 4 | B11: Artículo 35 - d | C11: ¿las tuberías que requieren recubrimiento térmico se encuentran en buen estado? | J11: =IF(I11="No cumple",0,IF(I11="No aplica",2,IF(I11="Cumple totalmente",2,IF(I11="Cumple parcialmente",1)))) -> FALSE
A12: 5 | B12: Artículo 35 - e | C12: ¿Las tuberías se mantienen en buen estado?¿Se controlan la fugas de inmediato? | J12: =IF(I12="No cumple",0,IF(I12="No aplica",2,IF(I12="Cumple totalmente",2,IF(I12="Cumple parcialmente",1)))) -> FALSE
A13: 6 | B13: Artículo 35 - f | C13: ¿La válvulas se mantienen en buen estado y se verifican antes de su operación? | J13: =IF(I13="No cumple",0,IF(I13="No aplica",2,IF(I13="Cumple totalmente",2,IF(I13="Cumple parcialmente",1)))) -> FALSE
A14: 7 | B14: Artículo 35 - g | C14: ¿Se cuenta con un sistema de prueba, monitoreo y alarma para detectar fugas de hidrogeno? | J14: =IF(I14="No cumple",0,IF(I14="No aplica",2,IF(I14="Cumple totalmente",2,IF(I14="Cumple parcialmente",1)))) -> FALSE
A15: 8 | B15: Artículo 35 - g | C15: ¿Se cuenta con procedimientos para el manejo de los cilindros de hidrógeno y programa de verificación periódica de los instrumentos medidores de control y protección del sistema? | J15: =IF(I15="No cumple",0,IF(I15="No aplica",2,IF(I15="Cumple totalmente",2,IF(I15="Cumple parcialmente",1)))) -> FALSE
A16: 9 | B16: Artículo 35 - h | C16: ¿Para labores de mantenimiento que se realicen a equipos que contengan hidrógeno se extrae el gas y se realizar una purga con el fin de verificar ausencia del mismo y se realiza medición atmosférica con equipo especializado? | J16: =IF(I16="No cumple",0,IF(I16="No aplica",2,IF(I16="Cumple totalmente",2,IF(I16="Cumple parcialmente",1)))) -> FALSE
A17: 10 | B17: Artículo 35 - i | C17: ¿En todos los equipos auxiliares cercanos al generador, se controlan los riesgos potenciales generadores de fuego, como fugas de aceites, acumulación de grasas, solventes, instalaciones eléctricas provisionales o en mal estado, procesos de soldadura, entre otros? | J17: =IF(I17="No cumple",0,IF(I17="No aplica",2,IF(I17="Cumple totalmente",2,IF(I17="Cumple parcialmente",1)))) -> FALSE
A18: N° | B18: ITEM | C18: CENTRAL TERMICA- Generación Térmica | I18: Calificación | J18: Puntaje
A19: 1 | B19: Artículo 36 | C19: ¿Se cuenta con indicaciones claras y precisas con respecto a no fumar y encender fuego en cercanía de las áreas de manejo de combustibles líquidos, gas o carbón de acuerdo a la normatividad vigente? | J19: =IF(I19="No cumple",0,IF(I19="No aplica",2,IF(I19="Cumple totalmente",2,IF(I19="Cumple parcialmente",1)))) -> FALSE
A20: 2 | B20: Artículo 36 | C20: ¿Se cuenta con procedimientos para la manipulación e intervención y el tipo de EPP a emplear en las plantas donde se requiera el uso de CO2 e hidrógeno? | J20: =IF(I20="No cumple",0,IF(I20="No aplica",2,IF(I20="Cumple totalmente",2,IF(I20="Cumple parcialmente",1)))) -> FALSE
A21: 3 | B21: Artículo 37 - a | C21: ¿Las fugas o derrames de combustible se reportan, controlan y corrigen de inmediato? | J21: =IF(I21="No cumple",0,IF(I21="No aplica",2,IF(I21="Cumple totalmente",2,IF(I21="Cumple parcialmente",1)))) -> FALSE
A22: 4 | B22: Artículo 37 - b | C22: ¿Se cuenta con procedimientos, permisos especiales para trabajos en caliente, se realiza control y seguimiento estricto a su ejecución? | J22: =IF(I22="No cumple",0,IF(I22="No aplica",2,IF(I22="Cumple totalmente",2,IF(I22="Cumple parcialmente",1)))) -> FALSE
A23: 5 | B23: Artículo 37 - c | C23: ¿Se controlan los límites máximos del nivel de los de tanques de almacenamiento de combustibles? | J23: =IF(I23="No cumple",0,IF(I23="No aplica",2,IF(I23="Cumple totalmente",2,IF(I23="Cumple parcialmente",1)))) -> FALSE
A24: 6 | B24: Artículo 37 - d | C24: ¿Se conecta a tierra el vehículo transportador de combustible y con algún sistema de protección contra incendio en el proceso de cargue y descargue de combustible? | J24: =IF(I24="No cumple",0,IF(I24="No aplica",2,IF(I24="Cumple totalmente",2,IF(I24="Cumple parcialmente",1)))) -> FALSE
A25: 7 | B25: Artículo 37 - e | C25: ¿Se realiza uso exclusivo de equipos de comunicación intrínsecamente seguros? | J25: =IF(I25="No cumple",0,IF(I25="No aplica",2,IF(I25="Cumple totalmente",2,IF(I25="Cumple parcialmente",1)))) -> FALSE
A26: 8 | B26: Artículo 37 - f | C26: ¿Se garantiza que los diques de contención de los tanques de almacenamiento de combustibles no presenten fisuras o grietas? | J26: =IF(I26="No cumple",0,IF(I26="No aplica",2,IF(I26="Cumple totalmente",2,IF(I26="Cumple parcialmente",1)))) -> FALSE
A27: 9 | B27: Artículo 37 - g | C27: ¿Se asegura que los venteos de seguridad o desfogue de los tanques de almacenamiento no estén obstruidos? | J27: =IF(I27="No cumple",0,IF(I27="No aplica",2,IF(I27="Cumple totalmente",2,IF(I27="Cumple parcialmente",1)))) -> FALSE
A28: 10 | B28: Artículo 37 - h | C28: ¿El agua que se sedimenta en el fondo es evacuada periódicamente, evitando acumulaciones.? | J28: =IF(I28="No cumple",0,IF(I28="No aplica",2,IF(I28="Cumple totalmente",2,IF(I28="Cumple parcialmente",1)))) -> FALSE
A29: 11 | B29: Artículo 37 - i | C29: ¿Se cuenta con procedimientos de trabajo en alturas y espacios confinados. Para ingresar a un tanque de combustible? | J29: =IF(I29="No cumple",0,IF(I29="No aplica",2,IF(I29="Cumple totalmente",2,IF(I29="Cumple parcialmente",1)))) -> FALSE
A30: 12 | B30: Artículo 38 - a | C30: ¿Se cuenta con sistemas de corte de flujo para casos de emergencia en el manejo de gas combustible ? | J30: =IF(I30="No cumple",0,IF(I30="No aplica",2,IF(I30="Cumple totalmente",2,IF(I30="Cumple parcialmente",1)))) -> FALSE
... A118: 100 | B118: Artículo 45 | C118: ¿Se cuenta con procedimientos de trabajo seguro para la inspección, operación y mantenimiento de los sistemas de manejo de cenizas volátiles? ¿al igual que los procedimientos para su transporte y disposición final de estos desechos. Teniendo en cuenta aspectos fundamentales tales como reglamentación de trabajo en Alturas, espacios confinados y aquellos que de acuerdo con las normas ambientales son vitales en la preservación y protección del medio ambiente? | J118: =IF(I118="No cumple",0,IF(I118="No aplica",2,IF(I118="Cumple totalmente",2,IF(I118="Cumple parcialmente",1)))) -> FALSE

Sheet C. Hidroeléctricas
A5: Seguros de Vida Suramericana S.A., ARL SURA. © Copyright – Marzo de 2021. Todos los derechos reservados.
A6: Resolución 5018 de 2019
A7: N° | B7: ITEM | C7: CENTRAL HIDROELECTRICA- Generalidades | I7: Calificación | J7: Puntaje
A8: 1 | B8: Artículo 35 - a | C8: ¿Las partes de maquinaria que se encuentren en movimiento permanecen protegidas? o ¿se cuenta con los métodos de control en el medio y distancias de seguridad? | J8: =IF(I8="No cumple",0,IF(I8="No aplica",2,IF(I8="Cumple totalmente",2,IF(I8="Cumple parcialmente",1)))) -> FALSE
A9: 2 | B9: Artículo 35 - b | C9: ¿Las tuberías y equipos cumple con el código de colores? | J9: =IF(I9="No cumple",0,IF(I9="No aplica",2,IF(I9="Cumple totalmente",2,IF(I9="Cumple parcialmente",1)))) -> FALSE
A10: 3 | B10: Artículo 35 - c | C10: ¿Las carátulas y ventanillas de los instrumentos indicadores o controladores se encuentran limpias y en buen estado? | J10: =IF(I10="No cumple",0,IF(I10="No aplica",2,IF(I10="Cumple totalmente",2,IF(I10="Cumple parcialmente",1)))) -> FALSE
A11: 4 | B11: Artículo 35 - d | C11: ¿las tuberías que requieren recubrimiento térmico se encuentran en buen estado? | J11: =IF(I11="No cumple",0,IF(I11="No aplica",2,IF(I11="Cumple totalmente",2,IF(I11="Cumple parcialmente",1)))) -> FALSE
A12: 5 | B12: Artículo 35 - e | C12: ¿Las tuberías se mantienen en buen estado?¿Se controlan la fugas de inmediato? | J12: =IF(I12="No cumple",0,IF(I12="No aplica",2,IF(I12="Cumple totalmente",2,IF(I12="Cumple parcialmente",1)))) -> FALSE
A13: 6 | B13: Artículo 35 - f | C13: ¿La válvulas se mantienen en buen estado y se verifican antes de su operación? | J13: =IF(I13="No cumple",0,IF(I13="No aplica",2,IF(I13="Cumple totalmente",2,IF(I13="Cumple parcialmente",1)))) -> FALSE
A14: 7 | B14: Artículo 35 - g | C14: ¿Se cuenta con un sistema de prueba, monitoreo y alarma para detectar fugas de hidrogeno? | J14: =IF(I14="No cumple",0,IF(I14="No aplica",2,IF(I14="Cumple totalmente",2,IF(I14="Cumple parcialmente",1)))) -> FALSE
A15: 8 | B15: Artículo 35 - g | C15: ¿Se cuenta con procedimientos para el manejo de los cilindros de hidrógeno y programa de verificación periódica de los instrumentos medidores de control y protección del sistema? | J15: =IF(I15="No cumple",0,IF(I15="No aplica",2,IF(I15="Cumple totalmente",2,IF(I15="Cumple parcialmente",1)))) -> FALSE
A16: 9 | B16: Artículo 35 - h | C16: ¿Para labores de mantenimiento que se realicen a equipos que contengan hidrógeno se extrae el gas y se realizar una purga con el fin de verificar ausencia del mismo y se realiza medición atmosférica con equipo especializado? | J16: =IF(I16="No cumple",0,IF(I16="No aplica",2,IF(I16="Cumple totalmente",2,IF(I16="Cumple parcialmente",1)))) -> FALSE
A17: 10 | B17: Artículo 35 - i | C17: ¿En todos los equipos auxiliares cercanos al generador, se controlan los riesgos potenciales generadores de fuego, como fugas de aceites, acumulación de grasas, solventes, instalaciones eléctricas provisionales o en mal estado, procesos de soldadura, entre otros? | J17: =IF(I17="No cumple",0,IF(I17="No aplica",2,IF(I17="Cumple totalmente",2,IF(I17="Cumple parcialmente",1)))) -> FALSE
A18: N° | B18: ITEM | C18: CENTRAL HIDROELECTRICA - Generación Térmica | I18: Calificación | J18: Puntaje
A19: 1 | B19: Artículo 46 - a | C19: ¿El vertedero cuenta con barandas de protección? | J19: =IF(I19="No cumple",0,IF(I19="No aplica",2,IF(I19="Cumple totalmente",2,IF(I19="Cumple parcialmente",1)))) -> FALSE
A20: 2 | B20: Artículo 46 - b | C20: ¿Existe señalización de los niveles del embalse e iluminación para su lectura cuando se requiera hacerlo en horas nocturnas? | J20: =IF(I20="No cumple",0,IF(I20="No aplica",2,IF(I20="Cumple totalmente",2,IF(I20="Cumple parcialmente",1)))) -> FALSE
A21: 3 | B21: Artículo 46 - c | C21: ¿La revisión de compuertas es realizada por personal capacitado.? | J21: =IF(I21="No cumple",0,IF(I21="No aplica",2,IF(I21="Cumple totalmente",2,IF(I21="Cumple parcialmente",1)))) -> FALSE
A22: 4 | B22: Artículo 46 - d | C22: ¿Existen seguros y candados en las casetas de control de las compuertas.? | J22: =IF(I22="No cumple",0,IF(I22="No aplica",2,IF(I22="Cumple totalmente",2,IF(I22="Cumple parcialmente",1)))) -> FALSE
A23: 5 | B23: Artículo 47 - a | C23: ¿Las embarcaciones, son revisadas verificando se encuentren en buenas condiciones antes de cada uso? | J23: =IF(I23="No cumple",0,IF(I23="No aplica",2,IF(I23="Cumple totalmente",2,IF(I23="Cumple parcialmente",1)))) -> FALSE
A24: 6 | B24: Artículo 47 - b | C24: ¿Las embarcaciones tienen pintada claramente en su costado la capacidad en kilogramos y número máximo de personas que pueden abordarla? Las cuales no se sobrepasan | J24: =IF(I24="No cumple",0,IF(I24="No aplica",2,IF(I24="Cumple totalmente",2,IF(I24="Cumple parcialmente",1)))) -> FALSE
A25: 7 | B25: Artículo 47 - c | C25: ¿Se cuenta con igual número de chaleco salvavidas al de su aforo? y no debe permitirse a ninguna persona estar a bordo, sin el chaleco salvavidas | J25: =IF(I25="No cumple",0,IF(I25="No aplica",2,IF(I25="Cumple totalmente",2,IF(I25="Cumple parcialmente",1)))) -> FALSE
A26: 8 | B26: Artículo 47 - d | C26: ¿Se cuenta a bordo con equipo de comunicaciones y recursos para atender emergencias? | J26: =IF(I26="No cumple",0,IF(I26="No aplica",2,IF(I26="Cumple totalmente",2,IF(I26="Cumple parcialmente",1)))) -> FALSE
A27: 9 | B27: Artículo 47 - e | C27: ¿La operación es realizada por personal autorizado, capacitado y certificado por la autoridad competente.? | J27: =IF(I27="No cumple",0,IF(I27="No aplica",2,IF(I27="Cumple totalmente",2,IF(I27="Cumple parcialmente",1)))) -> FALSE
A28: 10 | B28: Artículo 47 - f | C28: ¿Siempre se inicia su uso con los depósitos de combustible llenos? | J28: =IF(I28="No cumple",0,IF(I28="No aplica",2,IF(I28="Cumple totalmente",2,IF(I28="Cumple parcialmente",1)))) -> FALSE
A29: 11 | B29: Artículo 47 - g | C29: ¿Se tiene prohibido fumar o encender fuego? | J29: =IF(I29="No cumple",0,IF(I29="No aplica",2,IF(I29="Cumple totalmente",2,IF(I29="Cumple parcialmente",1)))) -> FALSE
A30: 12 | B30: Artículo 47 - h | C30: El operador de la embarcación es responsable de la seguridad del personal a bordo ¿los ocupantes reciben instrucciones específicas? | J30: =IF(I30="No cumple",0,IF(I30="No aplica",2,IF(I30="Cumple totalmente",2,IF(I30="Cumple parcialmente",1)))) -> FALSE
... A55: 37 | B55: Artículo 50 - d - 4 | C55: ¿Cuando se efectúen trabajos de reparación en el recinto rodete se cuenta con un sistema de extracción de aire? | J55: =IF(I55="No cumple",0,IF(I55="No aplica",2,IF(I55="Cumple totalmente",2,IF(I55="Cumple parcialmente",1)))) -> FALSE

Sheet L. Transmisión
A2: Seguros de Vida Suramericana S.A., ARL SURA. © Copyright – Marzo de 2021. Todos los derechos reservados.
A5: Resolución 5018 de 2019
A6: N° | B6: ITEM | C6: LÍNEAS DE TRANSMISIÓN - Generalidades | I6: Calificación | J6: Puntaje
A7: 1 | B7: Artículo 51 | C7: ¿Se cuenta con los árboles de carga y los límites de tensión máxima de los conductores y herrajes de los conjuntos de tracción? | J7: =IF(I7="No cumple",0,IF(I7="No aplica",2,IF(I7="Cumple totalmente",2,IF(I7="Cumple parcialmente",1)))) -> FALSE
A8: N° | B8: ITEM | C8: LÍNEAS DE TRANSMISIÓN - Construcción de Líneas | I8: Calificación | J8: Puntaje
A9: 2 | B9: Artículo 52 | C9: ¿Se cuenta con los respectivos proyectos y diseños acordes con las normas aplicables de seguridad y RETIE?. | J9: =IF(I9="No cumple",0,IF(I9="No aplica",2,IF(I9="Cumple totalmente",2,IF(I9="Cumple parcialmente",1)))) -> FALSE
A10: 3 | B10: Artículo 52 | C10: ¿Se cuenta con un punto de anclaje que garantice el desarrollo de la labor segura para levantar o hincar la estructura a construir? | J10: =IF(I10="No cumple",0,IF(I10="No aplica",2,IF(I10="Cumple totalmente",2,IF(I10="Cumple parcialmente",1)))) -> FALSE
C11: LÍNEAS DE TRANSMISIÓN- Trabajos sin tensión | I11: Calificación | J11: Puntaje
A12: 4 | B12: Artículo 53 - a | C12: ¿Se realiza apertura de todas las fuentes de energía? | J12: =IF(I12="No cumple",0,IF(I12="No aplica",2,IF(I12="Cumple totalmente",2,IF(I12="Cumple parcialmente",1)))) -> FALSE
A13: 5 | B13: Artículo 53 - a | C13: ¿En los sitios de trabajo donde no es posible verificar físicamente el corte visible, el jefe de trabajo valida y confirma mediante comunicación directa con el responsable de ejecutar las maniobras de operación? | J13: =IF(I13="No cumple",0,IF(I13="No aplica",2,IF(I13="Cumple totalmente",2,IF(I13="Cumple parcialmente",1)))) -> FALSE
A14: 6 | B14: Artículo 53 - b | C14: ¿Se realiza bloqueo o condenación, enclavamiento y señalización de los equipos de corte con los equipos recomendados por el fabricante? | J14: =IF(I14="No cumple",0,IF(I14="No aplica",2,IF(I14="Cumple totalmente",2,IF(I14="Cumple parcialmente",1)))) -> FALSE
A15: 7 | B15: Artículo 53 - c | C15: ¿Se realiza verificación de la ausencia de tensión? Para mejorar la confiabilidad de las medidas de ausencia de tensión en líneas de transmisión, el equipo de medida debe tener un dispositivo autónomo que verifique el correcto funcionamiento del equipo de medida | J15: =IF(I15="No cumple",0,IF(I15="No aplica",2,IF(I15="Cumple totalmente",2,IF(I15="Cumple parcialmente",1)))) -> FALSE
A16: 8 | B16: Artículo 53 - d | C16: ¿Se realiza instalación de sistemas de puesta a tierra y en cortocircuito lo más cerca posible del sitio donde se van a realizar los trabajos? En líneas de transmisión de Alta y Extra Alta Tensión, donde no sea posible hacer el corto circuito entre las fases, en cada sitio de trabajo se pondrá a tierra el conductor donde se está haciendo la intervención, ya sea a la estructura de la torre o al suelo, teniendo presente hacerlo lo más próximo al sitio de trabajo para evitar contactos con potenciales de electricidad estática presentes. | J16: =IF(I16="No cumple",0,IF(I16="No aplica",2,IF(I16="Cumple totalmente",2,IF(I16="Cumple parcialmente",1)))) -> FALSE
A17: 9 | B17: Artículo 53 - d | C17: ¿Los juegos de puesta a tierra de cable y conectores cumplen con las especificaciones de máxima corriente de falla prevista para la Sistemas de Alta Tensión (mínimo 40 kA)? | J17: =IF(I17="No cumple",0,IF(I17="No aplica",2,IF(I17="Cumple totalmente",2,IF(I17="Cumple parcialmente",1)))) -> FALSE
C18: LÍNEAS DE TRANSMISIÓN- Trabajos con tensión | I18: Calificación | J18: Puntaje
A19: 10 | B19: Artículo 54 | C19: ¿Para los trabajos con tensión los trabajadores cuentan con la respectiva habilitación vigente, con plan de trabajo previamente aprobado que describa las actividades paso a paso con las medidas de seguridad necesarias, y con la debida autorización de acuerdo con el procedimiento definido por cada empresa? | J19: =IF(I19="No cumple",0,IF(I19="No aplica",2,IF(I19="Cumple totalmente",2,IF(I19="Cumple parcialmente",1)))) -> FALSE
A20: 11 | B20: Artículo 54 | C20: ¿Se cuenta con plan de emergencia y personas responsables para la atención de primeros auxilios? | J20: =IF(I20="No cumple",0,IF(I20="No aplica",2,IF(I20="Cumple totalmente",2,IF(I20="Cumple parcialmente",1)))) -> FALSE
A21: 12 | B21: Artículo 54 | C21: ¿Antes de todo trabajo el personal ejecutor realiza una reunión previa y una inspección visual para verificar el estado de las instalaciones, los materiales y herramientas colectivas destinadas a la ejecución del mismo?. se debe Verificar visualmente que no existan descargas parciales, en el aislamiento del equipo a intervenir. | J21: =IF(I21="No cumple",0,IF(I21="No aplica",2,IF(I21="Cumple totalmente",2,IF(I21="Cumple parcialmente",1)))) -> FALSE
A22: 13 | B22: Artículo 54 | C22: ¿Para toda intervención de los equipos, de forma previa se realiza coordinación con el personal de protecciones, control y operación de la línea para verificar la seguridad operativa del sistema durante las maniobras y establecer los planes de emergencia operativos? | J22: =IF(I22="No cumple",0,IF(I22="No aplica",2,IF(I22="Cumple totalmente",2,IF(I22="Cumple parcialmente",1)))) -> FALSE
A23: 14 | B23: Artículo 55 | C23: ¿Para realizar trabajos con tensión en transmisión se utilizan solamente las herramientas, equipos diseñados y aprobados para el uso específico? además tener especial cuidado en el cumplimiento de los siguientes aspectos | J23: =IF(I23="No cumple",0,IF(I23="No aplica",2,IF(I23="Cumple totalmente",2,IF(I23="Cumple parcialmente",1)))) -> FALSE
A24: 15 | B24: Artículo 55 - a | C24: ¿Se realizan pruebas de rutina periódicamente para los equipos de trabajo con tensión de acuerdo con los procedimientos normalizados de nivel nacional o internacional?. Las herramientas que presenten valores de prueba fuera de los establecidos por el fabricante deben ser marcadas y retiradas de uso. | J24: =IF(I24="No cumple",0,IF(I24="No aplica",2,IF(I24="Cumple totalmente",2,IF(I24="Cumple parcialmente",1)))) -> FALSE
A25: 16 | B25: Artículo 55 - b | C25: ¿Se conoce la carga máxima mecánica a la tensión, a la flexión y torsión que soportan cada una de las herramientas que se utilicen de acuerdo con las fichas técnicas? nunca se debe sobrepasar esta carga | J25: =IF(I25="No cumple",0,IF(I25="No aplica",2,IF(I25="Cumple totalmente",2,IF(I25="Cumple parcialmente",1)))) -> FALSE
A26: 17 | B26: Artículo 55 - c | C26: ¿Al transportar las herramientas se evita someterlas a cizalladuras o roturas y cubrirlas con lonas u otro material de protección contra golpes y humedad? | J26: =IF(I26="No cumple",0,IF(I26="No aplica",2,IF(I26="Cumple totalmente",2,IF(I26="Cumple parcialmente",1)))) -> FALSE
A27: 18 | B27: Artículo 55 - d | C27: ¿Se colocan siempre las herramientas sobre una lona impermeable, nunca directamente en el suelo o sobre elementos cortantes? | J27: =IF(I27="No cumple",0,IF(I27="No aplica",2,IF(I27="Cumple totalmente",2,IF(I27="Cumple parcialmente",1)))) -> FALSE
A28: 19 | B28: Artículo 55 - e | C28: ¿Para ejecutar trabajos en equipos energizados, se cuenta previamente con la consignación, teniendo bloqueados los recierres en los extremos de alimentación de los circuitos a intervenir y de los que cruzan por debajo del vano o vanos intervenidos? | J28: =IF(I28="No cumple",0,IF(I28="No aplica",2,IF(I28="Cumple totalmente",2,IF(I28="Cumple parcialmente",1)))) -> FALSE
A29: 20 | B29: Artículo 55 - f | C29: ¿El responsable de la operación de la subestación, informa al jefe de trabajo sobre cualquier evento que ocurra en la subestación, para que el jefe de trabajo tome las decisiones pertinentes? | J29: =IF(I29="No cumple",0,IF(I29="No aplica",2,IF(I29="Cumple totalmente",2,IF(I29="Cumple parcialmente",1)))) -> FALSE
A30: 21 | B30: Artículo 55 - g | C30: ¿Se asegura el cumplimiento de las distancias mínimas de seguridad durante la ejecución de los trabajos? no disminuir las distancias de seguridad de acuerdo a la tensión nominal fase. En caso de tener duda de la distancia mínima, utilizar las pértigas aislantes para asegurar que se cumple con la distancia mínima | J30: =IF(I30="No cumple",0,IF(I30="No aplica",2,IF(I30="Cumple totalmente",2,IF(I30="Cumple parcialmente",1)))) -> FALSE
... A33: 24 | B33: Artículo 55 - j | C33: ¿Se realiza medición constante de la humedad relativa y corriente de fuga de los equipos aislados (Plataforma, andamio, escalera o helicóptero).? | J33: =IF(I33="No cumple",0,IF(I33="No aplica",2,IF(I33="Cumple totalmente",2,IF(I33="Cumple parcialmente",1)))) -> FALSE
C34: LÍNEAS DE TRANSMISIÓN-Trabajos con manejo de cargas en alturas y otras condiciones especiales | I34: Calificación | J34: Puntaje
A35: 25 | B35: Artículo 56 - b | C35: ¿Para toda carga que requiera estar suspendida y sometida a tracción mecánica se conoce su peso y volumen? con el objetivo de determinar los equipos y herramientas para su manipulación | J35: =IF(I35="No cumple",0,IF(I35="No aplica",2,IF(I35="Cumple totalmente",2,IF(I35="Cumple parcialmente",1)))) -> FALSE
A36: 26 | B36: Artículo 56-c | C36: ¿Todos los equipos utilizados para manipular una carga tienen un factor de seguridad de por lo menos 2.5 veces el peso de la carga suspendida? | J36: =IF(I36="No cumple",0,IF(I36="No aplica",2,IF(I36="Cumple totalmente",2,IF(I36="Cumple parcialmente",1)))) -> FALSE
A37: 27 | B37: Artículo 56-c | C37: ¿Al momento de utilizar equipos para manipular cargas se hace una inspección con el fin de verificar su estado y condición operativa? | J37: =IF(I37="No cumple",0,IF(I37="No aplica",2,IF(I37="Cumple totalmente",2,IF(I37="Cumple parcialmente",1)))) -> FALSE
A38: 28 | B38: Artículo 56-d | C38: ¿Para pasar herramienta o materiales entre diferentes niveles, se utilizan recipientes sujetados a la estructura para evitar la caída de este y el material que contenga? | J38: =IF(I38="No cumple",0,IF(I38="No aplica",2,IF(I38="Cumple totalmente",2,IF(I38="Cumple parcialmente",1)))) -> FALSE
A39: 29 | B39: Artículo 56 - e | C39: ¿Los elementos utilizados para el izaje de cargas, son independientes de los elementos utilizados para la protección de caída de alturas de las personas? | J39: =IF(I39="No cumple",0,IF(I39="No aplica",2,IF(I39="Cumple totalmente",2,IF(I39="Cumple parcialmente",1)))) -> FALSE
A40: 30 | B40: Artículo 57 - a | C40: ¿En la planeación de los trabajos de montaje y reparación de conductores aéreos se tienen en cuenta las características técnicas del conductor a intervenir, las cargas a las cuales está sometido cada conductor, la capacidad de carga y nivel de seguridad del tipo de estructura a intervenir al igual que las adyacentes? | J40: =IF(I40="No cumple",0,IF(I40="No aplica",2,IF(I40="Cumple totalmente",2,IF(I40="Cumple parcialmente",1)))) -> FALSE
A41: 31 | B41: Artículo 57 - b | C41: ¿Siempre que sea posible, se tiene como primera opción, la posibilidad de ejecutar el trabajo en línea desenergizada y con los conductores en el piso? | J41: =IF(I41="No cumple",0,IF(I41="No aplica",2,IF(I41="Cumple totalmente",2,IF(I41="Cumple parcialmente",1)))) -> FALSE
A42: 32 | B42: Artículo 57 - b | C42: ¿En caso de realizar trabajos en línea energizada se elabora un procedimiento que incluya el análisis de estabilidad mecánica de la estructura y los conductores que serán sometidos a cargas y que proteja contra caídas al personal habilitado? | J42: =IF(I42="No cumple",0,IF(I42="No aplica",2,IF(I42="Cumple totalmente",2,IF(I42="Cumple parcialmente",1)))) -> FALSE
A43: 33 | B43: Artículo 57 - c | C43: Se planea con la debida anticipación y se establecen los procedimientos para el ascenso, descenso y desplazamiento sobre el conductor o conductores y estructuras, al igual que el esquema de protección con línea de vida para el personal habilitado buscando puntos de anclaje diferentes al conductor intervenido, y la selección detallada de los equipos y dispositivos necesarios, así como los criterios y procedimientos para cada etapa del trabajo, las condiciones para un eventual rescate de algún personal habilitado.? | J43: =IF(I43="No cumple",0,IF(I43="No aplica",2,IF(I43="Cumple totalmente",2,IF(I43="Cumple parcialmente",1)))) -> FALSE
A44: 34 | B44: Artículo 58 | C44: ¿La empresa dispone de un procedimiento normalizado para la atención de emergencias donde expliquen los aspectos técnicos, se identifiquen los riesgos y las medidas de prevención y protección para las personas y el medio ambiente? | J44: =IF(I44="No cumple",0,IF(I44="No aplica",2,IF(I44="Cumple totalmente",2,IF(I44="Cumple parcialmente",1)))) -> FALSE
A45: 35 | B45: Artículo 58 | C45: ¿Para los sitios de trabajo donde se han presentado atentados terroristas y se presume existencia de minas antipersona, se solicita a la fuerza pública, que luego de hacer la revisión protocolaria, entregue la zona de trabajo delimitada e imparta las indicaciones para prevenir cualquier accidente con explosivos? | J45: =IF(I45="No cumple",0,IF(I45="No aplica",2,IF(I45="Cumple totalmente",2,IF(I45="Cumple parcialmente",1)))) -> FALSE
A46: 36 | B46: Artículo 59 | C46: ¿Los trabajadores que ejecuten actividades de pintura o recubrimiento de estructuras y equipos se protegen con elementos de protección personal acordes con los riesgos generados por los componentes químicos de las pinturas, solventes y anticorrosivos utilizados? | J46: =IF(I46="No cumple",0,IF(I46="No aplica",2,IF(I46="Cumple totalmente",2,IF(I46="Cumple parcialmente",1)))) -> FALSE
... A48: 38 | B48: Artículo 60 | C48: ¿Para los trabajos de obras civiles y obras de protección de estructuras en líneas de transmisión, se procede de acuerdo con lo estipulado en las normas vigentes de seguridad para la ejecución de obras de construcción civil y espacios confinados? vigilar el cumplimiento de lo estipulado en la legislación vigente en materia de gestión ambiental en cuanto al uso y aprovechamiento de los recursos naturales | J48: =IF(I48="No cumple",0,IF(I48="No aplica",2,IF(I48="Cumple totalmente",2,IF(I48="Cumple parcialmente",1)))) -> FALSE

Sheet Redes de distribución
A2: Seguros de Vida Suramericana S.A., ARL SURA. © Copyright – Marzo de 2021. Todos los derechos reservados.
A5: Resolución 5018 de 2019
A6: N° | B6: ITEM | C6: REDES DE DISTRIBUCIÓN- Generalidades | I6: Calificación | J6: Puntaje
A7: 1 | B7: Artículo 61 - a | C7: ¿El jefe de trabajo, supervisor o coordinador informa a la central, subestación o centro de control correspondiente los trabajos a realizar, asegurando las comunicaciones en doble vía, repitiendo el mensaje? | J7: =IF(I7="No cumple",0,IF(I7="No aplica",2,IF(I7="Cumple totalmente",2,IF(I7="Cumple parcialmente",1)))) -> FALSE
A8: 2 | B8: Artículo 61 - b | C8: ¿Se solicita la normalización del circuito, esperando la confirmación y verificando su funcionamiento? | J8: =IF(I8="No cumple",0,IF(I8="No aplica",2,IF(I8="Cumple totalmente",2,IF(I8="Cumple parcialmente",1)))) -> FALSE
A9: 3 | B9: Artículo 62 | C9: ¿Todo operador de red establece, divulgar y controlar el cumplimiento de los requisitos técnicos y de seguridad que deben tener los terceros (empresas o personas) que interactúen con sus redes o infraestructura.? | J9: =IF(I9="No cumple",0,IF(I9="No aplica",2,IF(I9="Cumple totalmente",2,IF(I9="Cumple parcialmente",1)))) -> FALSE
A10: 4 | B10: Artículo 63 | C10: ¿Se cuenta como mínimo con dos trabajadores laborando en conjunto que cumplan con la normatividad vigente para trabajos en altura? (Resolución 1409 de 1012 o aquellas modifique, adicione o sustituya) | J10: =IF(I10="No cumple",0,IF(I10="No aplica",2,IF(I10="Cumple totalmente",2,IF(I10="Cumple parcialmente",1)))) -> FALSE
A11: 5 | B11: Artículo 64 | C11: ¿Cuando se ejecuten trabajos sobre circuitos que vayan paralelos o se crucen con otros de mayor o menor tensión y no se garanticen las distancias de seguridad establecidas , se desenergizan los circuitos involucrados o se aíslan eléctricamente por medio de cubiertas según el nivel de tensión? Este trabajo debe ser realizado por Grupo de Trabajos con tensión. T.C.T. | J11: =IF(I11="No cumple",0,IF(I11="No aplica",2,IF(I11="Cumple totalmente",2,IF(I11="Cumple parcialmente",1)))) -> FALSE
A12: 6 | B12: Artículo 65 | C12: ¿Se tiene definido el tiempo de espera por la empresa, de acuerdo con las características de los capacitores posterior a la desconexión de los mismos? | J12: =IF(I12="No cumple",0,IF(I12="No aplica",2,IF(I12="Cumple totalmente",2,IF(I12="Cumple parcialmente",1)))) -> FALSE
A13: 7 | B13: Artículo 65 | C13: ¿Se cortocircuitan las terminales y se conecta a tierra la carcasa del capacitor antes de iniciar los trabajos? Los condensadores no se deben abrir con tensión | J13: =IF(I13="No cumple",0,IF(I13="No aplica",2,IF(I13="Cumple totalmente",2,IF(I13="Cumple parcialmente",1)))) -> FALSE
A14: 8 | B14: Artículo 66 | C14: ¿Cuando se va a trabajar un circuito donde se desenergizó a través de la apertura de un reconectador, se asegura que se encuentre bloqueado el cierre remoto y el local.? | J14: =IF(I14="No cumple",0,IF(I14="No aplica",2,IF(I14="Cumple totalmente",2,IF(I14="Cumple parcialmente",1)))) -> FALSE
A15: 9 | B15: Artículo 67 | C15: ¿Cuando se instalen equipos de seccionamiento que no tengan corte visible se garantiza que estos dispongan de mecanismo de corte efectivo para evitar recierres por parte del centro de control? | J15: =IF(I15="No cumple",0,IF(I15="No aplica",2,IF(I15="Cumple totalmente",2,IF(I15="Cumple parcialmente",1)))) -> FALSE
A16: 10 | B16: Artículo 68 | C16: ¿Los cortacircuitos, seccionadores o cuchillas se operan sin carga?, para lo cual se debe solicitar la desenergización del circuito. Si esto no es posible se deben operar utilizando un equipo que extinga el arco. | J16: =IF(I16="No cumple",0,IF(I16="No aplica",2,IF(I16="Cumple totalmente",2,IF(I16="Cumple parcialmente",1)))) -> FALSE
A17: 11 | B17: Artículo 69 | C17: ¿La empresa tiene documentado sus procedimientos para el montaje o desmontaje de los elementos del sistema? en los cuales aparecerá de manera secuencial el orden de conexiones o desconexiones y las acciones a seguir en caso de identificar una condición de riesgo. | J17: =IF(I17="No cumple",0,IF(I17="No aplica",2,IF(I17="Cumple totalmente",2,IF(I17="Cumple parcialmente",1)))) -> FALSE
A18: 12 | B18: Artículo 70 - a | C18: ¿Se cuenta con ayudas mecánicas para el tendido y tensionado de conductores? | J18: =IF(I18="No cumple",0,IF(I18="No aplica",2,IF(I18="Cumple totalmente",2,IF(I18="Cumple parcialmente",1)))) -> FALSE
... A25: 19 | B25: Artículo 71 - c | C25: ¿Se busca y elimina, en la red o en el transformador, la falla que ocasionó la fusión de la protección? | J25: =IF(I25="No cumple",0,IF(I25="No aplica",2,IF(I25="Cumple totalmente",2,IF(I25="Cumple parcialmente",1)))) -> FALSE
A26: N° | B26: ITEM | C26: REDES DE DISTRIBUCIÓN - Trabajos en baja y media tensión | I26: Calificación | J26: Puntaje
A27: 20 | B27: Artículo 72 - a | C27: ¿El operario técnico de trabajos con tensión cumple con el perfil requerido? Experiencia mínima de 2 años en mantenimiento o construcción de redes de media tensión sin tensión La formación para el aspirante debe estar claramente definida en el proceso de habilitación. En el que además deberá estipularse un período de tiempo de trabajo con acompañamiento activo por parte de personal habilitado para TCT no inferior a 120 horas. | J27: =IF(I27="No cumple",0,IF(I27="No aplica",2,IF(I27="Cumple totalmente",2,IF(I27="Cumple parcialmente",1)))) -> FALSE
A28: 21 | B28: Artículo 72 - b | C28: ¿Se establece un método para que el trabajador pase de conformar un equipo de Trabajo con tensión a realizar trabajos en línea desenergizada? Reinducción previa que permita el afianzamiento a los procedimientos y adaptación al trabajo en línea desenergizada; lo anterior debe ser avalado por la empresa | J28: =IF(I28="No cumple",0,IF(I28="No aplica",2,IF(I28="Cumple totalmente",2,IF(I28="Cumple parcialmente",1)))) -> FALSE
A29: 22 | B29: Artículo 72 - c | C29: El personal de Trabajo con tensión recibe una reinducción y actualización anual, específica para esta labor, el total de horas de capacitación debe ser superior a 40 horas. | J29: =IF(I29="No cumple",0,IF(I29="No aplica",2,IF(I29="Cumple totalmente",2,IF(I29="Cumple parcialmente",1)))) -> FALSE
A30: 23 | B30: Artículo 72 - d | C30: ¿Se practican exámenes médicos de ingreso y periódico anual para constatar el estado de salud, condición física y mental y su aptitud para este tipo de trabajo? No son aptos para el oficio personas con marcapasos, prótesis u órtesis metálicas | J30: =IF(I30="No cumple",0,IF(I30="No aplica",2,IF(I30="Cumple totalmente",2,IF(I30="Cumple parcialmente",1)))) -> FALSE
A31: 24 | B31: Artículo 73 - a | C31: ¿El trabajo con tensión se realiza tal y como fue planeado? | J31: =IF(I31="No cumple",0,IF(I31="No aplica",2,IF(I31="Cumple totalmente",2,IF(I31="Cumple parcialmente",1)))) -> FALSE
A32: 25 | B32: Artículo 73 - a | C32: ¿Cualquier variación en lo planeado se explica por el jefe de trabajos de forma detallada al personal, verificando que haya sido entendida? | J32: =IF(I32="No cumple",0,IF(I32="No aplica",2,IF(I32="Cumple totalmente",2,IF(I32="Cumple parcialmente",1)))) -> FALSE
A33: 26 | B33: Artículo 73 - b | C33: ¿Cada integrante del grupo tiene la responsabilidad del cumplimiento de todas las normas de seguridad, procedimientos, técnicas y métodos de trabajo? | J33: =IF(I33="No cumple",0,IF(I33="No aplica",2,IF(I33="Cumple totalmente",2,IF(I33="Cumple parcialmente",1)))) -> FALSE
A34: 27 | B34: Artículo 73 - c | C34: ¿El cubrimiento de las redes se instala progresivamente iniciando por la zona más próxima a las personas habilitadas, sin dejar en su recorrido puntos descubiertos. De igual forma, las cubiertas se retiran a medida que se vaya “saliendo” de la zona de trabajo? | J34: =IF(I34="No cumple",0,IF(I34="No aplica",2,IF(I34="Cumple totalmente",2,IF(I34="Cumple parcialmente",1)))) -> FALSE
A35: 28 | B35: Artículo 73 - d | C35: ¿Se mantienen los equipos y conductores de otras fases, que puedan ser alcanzados en forma accidental o voluntaria, completamente cubiertos? ¿Se asegura que el trabajo únicamente se realiza en una sola fase? | J35: =IF(I35="No cumple",0,IF(I35="No aplica",2,IF(I35="Cumple totalmente",2,IF(I35="Cumple parcialmente",1)))) -> FALSE
A36: 29 | B36: Artículo 73 - e | C36: ¿En los casos de circuitos en postes o estructuras de madera, se tiene en cuenta que todas las partes de madera se encuentran potencialmente a tierra? | J36: =IF(I36="No cumple",0,IF(I36="No aplica",2,IF(I36="Cumple totalmente",2,IF(I36="Cumple parcialmente",1)))) -> FALSE
A37: 30 | B37: Artículo 73 - f | C37: ¿Se prioriza la seguridad por la rapidez en la ejecución de trabajos en labores de mantenimiento de redes en TCT? | J37: =IF(I37="No cumple",0,IF(I37="No aplica",2,IF(I37="Cumple totalmente",2,IF(I37="Cumple parcialmente",1)))) -> FALSE
A38: 31 | B38: Artículo 73 - g | C38: ¿Se tiene prohibido trabajar con la técnica de TCT en un circuito que presente falla? | J38: =IF(I38="No cumple",0,IF(I38="No aplica",2,IF(I38="Cumple totalmente",2,IF(I38="Cumple parcialmente",1)))) -> FALSE
... A47: 40 | B47: Artículo 75 - e | C47: ¿Para el montaje y desmonte de luminarias se garantiza el cumplimiento de las distancias mínimas de seguridad, considerando la longitud del brazo? | J47: =IF(I47="No cumple",0,IF(I47="No aplica",2,IF(I47="Cumple totalmente",2,IF(I47="Cumple parcialmente",1)))) -> FALSE
A48: N° | B48: ITEM | C48: REDES DE DISTRIBUCIÓN - Trabajos en redes de distribución subterráneas | I48: Calificación | J48: Puntaje
A49: 41 | B49: Artículo 76 - a | C49: ¿En instalaciones subterráneas se realiza señalización y demarcación del área de trabajo? | J49: =IF(I49="No cumple",0,IF(I49="No aplica",2,IF(I49="Cumple totalmente",2,IF(I49="Cumple parcialmente",1)))) -> FALSE
A50: 42 | B50: Artículo 76 - b | C50: ¿En instalaciones subterráneas se abre cámara para permitir escape de gases y ventilación natural? | J50: =IF(I50="No cumple",0,IF(I50="No aplica",2,IF(I50="Cumple totalmente",2,IF(I50="Cumple parcialmente",1)))) -> FALSE
A51: 43 | B51: Artículo 76 - c | C51: ¿Se garantiza que el equipo de trabajo cuente con un sistema de monitoreo de gases durante todo el tiempo de permanencia en la cámara subterránea? | J51: =IF(I51="No cumple",0,IF(I51="No aplica",2,IF(I51="Cumple totalmente",2,IF(I51="Cumple parcialmente",1)))) -> FALSE
A52: 44 | B52: Artículo 76 - d | C52: ¿Antes de entrar a una cámara subterránea, su atmósfera interior es evaluada para determinar si existen gases tóxicos, combustibles o inflamables, con niveles por encima de los límites permisibles y la concentración de oxígeno mínima? Si la concentración del gas es superior al valor límite permisible ¿Se implementa un sistema de ventilación forzada continua hasta llegar al nivel permitido? Mientras la concentración de oxígeno esté por fuera de los valores límites permisibles, no se efectuará el trabajo. En todo caso se deberá aplicar la normatividad legal vigente | J52: =IF(I52="No cumple",0,IF(I52="No aplica",2,IF(I52="Cumple totalmente",2,IF(I52="Cumple parcialmente",1)))) -> FALSE
A53: 45 | B53: Artículo 76 - e | C53: ¿Se inspeccionan las condiciones detectando deficiencias en la estructura y otros peligros, con el fin de implementar las medidas que deben adoptarse para evitar accidentes? | J53: =IF(I53="No cumple",0,IF(I53="No aplica",2,IF(I53="Cumple totalmente",2,IF(I53="Cumple parcialmente",1)))) -> FALSE
A54: 46 | B54: Artículo 76 - f | C54: ¿En instalaciones subterráneas se drena cuando exista acumulación de agua? | J54: =IF(I54="No cumple",0,IF(I54="No aplica",2,IF(I54="Cumple totalmente",2,IF(I54="Cumple parcialmente",1)))) -> FALSE
A55: 47 | B55: Artículo 76 - g | C55: ¿Se planea la posible acción de rescate que resulte necesaria, de acuerdo a los riesgos existentes y a las características de la instalación. Se debe garantiza que el equipo de trabajo cuente con un procedimiento de rescate en situaciones de emergencia? | J55: =IF(I55="No cumple",0,IF(I55="No aplica",2,IF(I55="Cumple totalmente",2,IF(I55="Cumple parcialmente",1)))) -> FALSE
A56: 48 | B56: Artículo 76 - h | C56: ¿Previo al ingreso a una cámara subterránea el trabajador tiene un sistema de protección contra caída que permita su rescate desde el exterior en caso de accidente? | J56: =IF(I56="No cumple",0,IF(I56="No aplica",2,IF(I56="Cumple totalmente",2,IF(I56="Cumple parcialmente",1)))) -> FALSE
A57: 49 | B57: Artículo 76 - i | C57: ¿Para ingresar a la cámara de inspección o subestación de sótano se utilizan escaleras de material no conductor que apoye firme y completamente en el piso? No deben utilizarse los cables o estructuras como peldaños para bajar | J57: =IF(I57="No cumple",0,IF(I57="No aplica",2,IF(I57="Cumple totalmente",2,IF(I57="Cumple parcialmente",1)))) -> FALSE
A58: 50 | B58: Artículo 76 - j | C58: ¿Antes de iniciar cualquier trabajo, se identifican todos los circuitos, trayectorias, circuitos de alimentación, transformadores y medios de seccionamiento que involucren los trabajos a desarrollar de acuerdo al diagrama unifilar actualizado? | J58: =IF(I58="No cumple",0,IF(I58="No aplica",2,IF(I58="Cumple totalmente",2,IF(I58="Cumple parcialmente",1)))) -> FALSE
A59: 51 | B59: Artículo 77 - a | C59: ¿Los cables de media y de baja tensión, transformadores y equipos asociados se encuentran debidamente identificados de acuerdo a normas vigentes? debiendo coincidir con lo señalado en los planos de las instalaciones | J59: =IF(I59="No cumple",0,IF(I59="No aplica",2,IF(I59="Cumple totalmente",2,IF(I59="Cumple parcialmente",1)))) -> FALSE
A60: 52 | B60: Artículo 77 - b | C60: ¿Cuando se encuentre una instalación que no cumpla con el requisito se reporta de inmediato a la dependencia correspondiente? y no se debe realizar ningún trabajo hasta tanto sean debidamente identificados los circuitos involucrados | J60: =IF(I60="No cumple",0,IF(I60="No aplica",2,IF(I60="Cumple totalmente",2,IF(I60="Cumple parcialmente",1)))) -> FALSE
... A85: 77 | B85: Artículo 80 - d | C85: ¿Todo cambio en la configuración de los circuitos, derivado de maniobras de concordancia de fase o transferencia de cargas, o por cualquier otro motivo, se registra oportunamente en los centros de control, manteniéndose los planos correspondientes actualizados y se comunica al personal los cambios adoptados? | J85: =IF(I85="No cumple",0,IF(I85="No aplica",2,IF(I85="Cumple totalmente",2,IF(I85="Cumple parcialmente",1)))) -> FALSE

Sheet Comercialización
A5: Seguros de Vida Suramericana S.A., ARL SURA. © Copyright – Marzo de 2021. Todos los derechos reservados.
A6: Resolución 5018 de 2019
A7: N° | B7: ITEM | C7: COMERCIALIZACION - Generalidades | I7: Calificación | J7: Puntaje
A8: 1 | B8: Artículo 81 | C8: La organización en las actividades de comercialización cuenta con procedimientos documentados, divulgados y actualizados cada vez que se presenten cambios en procesos, tecnologías, riesgos? | J8: =IF(I8="No cumple",0,IF(I8="No aplica",2,IF(I8="Cumple totalmente",2,IF(I8="Cumple parcialmente",1)))) -> FALSE
A9: 2 | B9: Artículo 81 | C9: La organización para las actividades en las que se manipulen o se trabaje en cercanía de circuitos de media y baja tensión utiliza elementos de protección personal de acuerdo con el nivel de riesgo por contacto directo o indirecto y arco eléctrico.? | J9: =IF(I9="No cumple",0,IF(I9="No aplica",2,IF(I9="Cumple totalmente",2,IF(I9="Cumple parcialmente",1)))) -> FALSE
A10: 3 | B10: Artículo 81 | C10: La organización tiene establecido el uso de herramientas con el aislamiento y dando cumplimiento a la normatividad nacional o internacional vigente (o aquellas que Ia modifique, adicione o sustituya) y los equipos acordes al nivel de tensión que se utilicen? | J10: =IF(I10="No cumple",0,IF(I10="No aplica",2,IF(I10="Cumple totalmente",2,IF(I10="Cumple parcialmente",1)))) -> FALSE
A11: 4 | B11: Artículo 81 | C11: La organización tiene establecido para las actividades que requieran el acceso, contacto, apertura o cierre de circuitos de media tensión, la programación y consignación de elementos de la red con el centro de control? | J11: =IF(I11="No cumple",0,IF(I11="No aplica",2,IF(I11="Cumple totalmente",2,IF(I11="Cumple parcialmente",1)))) -> FALSE
C12: COMERCIALIZACION- Medición, corte, suspensión, reconexión, reinstalación | I12: Calificación | J12: Puntaje
A13: 5 | B13: Artículo 82 | C13: La organización establece para las actividades relacionadas con medición, el diligenciamiento del formato preoperacional en el que se incluyan la identificación de peligros y el establecimiento de controles antes de Ia ejecución de toda actividad? | J13: =IF(I13="No cumple",0,IF(I13="No aplica",2,IF(I13="Cumple totalmente",2,IF(I13="Cumple parcialmente",1)))) -> FALSE
A14: 6 | B14: Artículo 82 | C14: Se realiza el uso adecuado de los elementos de protección personal y elementos de protección contra caídas requeridos de acuerdo al nivel de tensión, y riesgo por arco eléctrico? | J14: =IF(I14="No cumple",0,IF(I14="No aplica",2,IF(I14="Cumple totalmente",2,IF(I14="Cumple parcialmente",1)))) -> FALSE
A15: 7 | B15: Artículo 82 | C15: Las cajas o encerramientos metálicos en los que no se puede evidenciar la puesta a tierra, se considerara como energizadas a la tensión mas alta de los circuitos que contengan. ¿Se realiza la validación? | J15: =IF(I15="No cumple",0,IF(I15="No aplica",2,IF(I15="Cumple totalmente",2,IF(I15="Cumple parcialmente",1)))) -> FALSE
A16: 8 | B16: Artículo 82 | C16: La instalación o retiro de medidores se realiza desconectando previamente Ia carga y usando herramienta aislada, guantes aislados según nivel de tensión y protección para arco eléctrico?. Los conductores eléctricos desconectados se encuentran sin su correspondiente aislamiento? | J16: =IF(I16="No cumple",0,IF(I16="No aplica",2,IF(I16="Cumple totalmente",2,IF(I16="Cumple parcialmente",1)))) -> FALSE
A17: 9 | B17: Artículo 82 | C17: La organización contempla para la instalación de medidores con tensión en la acometida que, primero se conecte a tierra el medidor, posteriormente el neutro y finalmente las fases, una a una, según su marcación? | J17: =IF(I17="No cumple",0,IF(I17="No aplica",2,IF(I17="Cumple totalmente",2,IF(I17="Cumple parcialmente",1)))) -> FALSE
A18: 10 | B18: Artículo 82 | C18: La organización tiene establecido para el retiro de medidores con tensión en la acometida la desconexión de las fases, una a una según su marcación, luego el neutro y finalmente la puesta a tierra? | J18: =IF(I18="No cumple",0,IF(I18="No aplica",2,IF(I18="Cumple totalmente",2,IF(I18="Cumple parcialmente",1)))) -> FALSE
A19: 11 | B19: Artículo 82 | C19: La organización tiene establecido para el retiro de medidor el aislamiento y señalización de los conductores de fase, neutro y tierra, para facilitar su debida identificación en maniobras posteriores.? | J19: =IF(I19="No cumple",0,IF(I19="No aplica",2,IF(I19="Cumple totalmente",2,IF(I19="Cumple parcialmente",1)))) -> FALSE
A20: 12 | B20: Artículo 82 | C20: La organización tiene establecido en el procedimiento de señalización que, toda área de trabajo se señalice y delimite sin ningún tipo de excepción. | J20: =IF(I20="No cumple",0,IF(I20="No aplica",2,IF(I20="Cumple totalmente",2,IF(I20="Cumple parcialmente",1)))) -> FALSE
A21: 13 | B21: Artículo 83 | C21: Para las actividades de corte, suspensión reconexión y reinstalación se contempla en procedimiento de señalización y demarcación de las áreas de trabajo con el fin de aislar la zona de personal ajeno al grupo de trabajo.? | J21: =IF(I21="No cumple",0,IF(I21="No aplica",2,IF(I21="Cumple totalmente",2,IF(I21="Cumple parcialmente",1)))) -> FALSE
A22: 14 | B22: Artículo 83 | C22: La organización establece el procedimiento para realizar la verificación de tensión y corriente al momento de realizar Ia reconexión o Ia reinstalación. | J22: =IF(I22="No cumple",0,IF(I22="No aplica",2,IF(I22="Cumple totalmente",2,IF(I22="Cumple parcialmente",1)))) -> FALSE
A23: 15 | B23: Artículo 83 | C23: La organización establece para el proceso de corte o suspensión del servicio de energía la desconexión de las fases, una a una según su marcación y luego el neutro y establece los requisitos para los terminales y su respectivo aislamiento? | J23: =IF(I23="No cumple",0,IF(I23="No aplica",2,IF(I23="Cumple totalmente",2,IF(I23="Cumple parcialmente",1)))) -> FALSE
A24: 16 | B24: Artículo 83 | C24: La organización tiene definido para el proceso de reconexión o reinstalación del servicio de energía la actividad de conectar primero el neutro y luego las fases, una a una según su marcación. | J24: =IF(I24="No cumple",0,IF(I24="No aplica",2,IF(I24="Cumple totalmente",2,IF(I24="Cumple parcialmente",1)))) -> FALSE
C25: COMERCIALIZACION - Cuentas nuevas, revisiones | I25: Calificación | J25: Puntaje
A26: 17 | B26: Artículo 84 | C26: Para las actividades de obra civil que incluye corte y perforación en estructuras, para la instalación de nuevas celdas de medida y medidores se tiene contemplado realizar cumpliendo las distancias de seguridad con redes de baja y media tensión; en caso contrario en las que no sea posible cumplir las distancias se realiza el trabajo en acometidas y/o barrajes des energizados? | J26: =IF(I26="No cumple",0,IF(I26="No aplica",2,IF(I26="Cumple totalmente",2,IF(I26="Cumple parcialmente",1)))) -> FALSE
A27: 18 | B27: Artículo 85 | C27: En las actividades donde existe el riesgo de proyección de partículas, golpes, laceraciones entre otras, el empleador tiene establecido suministrar y garantizar su uso, de elementos de protección personal acordes sin desproteger ante posibles peligros eléctricos? | J27: =IF(I27="No cumple",0,IF(I27="No aplica",2,IF(I27="Cumple totalmente",2,IF(I27="Cumple parcialmente",1)))) -> FALSE
A28: 19 | B28: Artículo 86 | C28: La organización tiene establecido para la realización de pruebas de funcionamiento de medidores, transformadores de corriente (TC) y transformadores de potencial (TP), se deben utilizar equipos y/o herramientas, que garanticen la seguridad del trabajador y de terceros, referente a riesgo eléctrico, de quemaduras y de incendio; este procedimiento incluye protección a fallas eléctricas y aislamiento térmico, los terminales o puntos de conexión son compatibles con los distintos tipos de barrajes? | J28: =IF(I28="No cumple",0,IF(I28="No aplica",2,IF(I28="Cumple totalmente",2,IF(I28="Cumple parcialmente",1)))) -> FALSE
A29: 20 | B29: Artículo 87 | C29: Se tiene establecido en el procedimiento la Identificación y marcaje de los bajantes secundarios del punto o transformador, dejando clara la entrada o alimentación de los bajantes y la salida a la carga o alimentación del circuito? | J29: =IF(I29="No cumple",0,IF(I29="No aplica",2,IF(I29="Cumple totalmente",2,IF(I29="Cumple parcialmente",1)))) -> FALSE
A30: 21 | B30: Artículo 88 | C30: La organización para el proceso de macro medición tiene establecido el procedimiento para cumplimiento de las 5 reglas de oro para trabajo en redes sin tensión? | J30: =IF(I30="No cumple",0,IF(I30="No aplica",2,IF(I30="Cumple totalmente",2,IF(I30="Cumple parcialmente",1)))) -> FALSE
C31: COMERCIALIZACION - Lectura de medidores | I31: Calificación | J31: Puntaje
A32: 22 | B32: Artículo 89 | C32: Para el proceso de toma de lectura de medidores el personal ejecutante cuenta con formación y/o capacitación en riesgo eléctrico y en identificación y control de los riesgos adicionales que la ejecución de la tarea le demande. El personal se encuentra incluido en los programas de formación especifica en riesgo eléctrico por parte de la empresa. | J32: =IF(I32="No cumple",0,IF(I32="No aplica",2,IF(I32="Cumple totalmente",2,IF(I32="Cumple parcialmente",1)))) -> FALSE
A33: 23 | B33: Artículo 90 | C33: El personal que realiza actividades de lectura de medidores cuenta con formación en distancias de seguridad de acuerdo con el nivel de tensión.? | J33: =IF(I33="No cumple",0,IF(I33="No aplica",2,IF(I33="Cumple totalmente",2,IF(I33="Cumple parcialmente",1)))) -> FALSE
A34: 24 | B34: Artículo 91 | C34: El personal que realiza la apertura, manipulación y acceso a celdas de medida se encuentra habilitado, avalado por la empresa y con los elementos de protección personal para contacto directo indirecto y de protección contra arco eléctrico? | J34: =IF(I34="No cumple",0,IF(I34="No aplica",2,IF(I34="Cumple totalmente",2,IF(I34="Cumple parcialmente",1)))) -> FALSE

Sheet Lista
C1: Nombre | D1: Valor
C2: No aplica | D2: 2
C3: No cumple | D3: 0
C4: Cumple parcialmente | D4: 1
C5: Cumple totalmente | D5: 2

Sheet Resultados
A2: Seguros de Vida Suramericana S.A., ARL SURA. © Copyright – Marzo de 2021. Todos los derechos reservados.
A3: RESUMEN DE LA LÍNEA BASAL RESOLUCIÓN 5018 DE 2019
A4: Porcentaje de implementación
A5: Elemento a evaluar | B5: Puntaje posible | C5: Puntaje obtenido | D5: Porcentaje de calificación real | E5: Porcentaje ponderado de implementación
A6: SST Sector eléctrico y actividades relacionadas | B6: 226 | C6: =SUM('SST sector EL. y Actividades'!J8:J129) -> 164 | D6: =C6/B6 -> 0.72566372 | E6: =(D6*16.6666%) -> 0.12094347
A7: Centrales térmicas | B7: 220 | C7: =SUM('Centrales Térmicas'!J8:J118) -> 0 | D7: =C7/B7 -> 0 | E7: =(D7*16.6666%) -> 0
A8: Centrales hidroeléctricas | B8: 94 | C8: =SUM('C. Hidroeléctricas'!J8:J55) -> 0 | D8: =C8/B8 -> 0 | E8: =(D8*16.6666%) -> 0
A9: L. Transmisión | B9: 76 | C9: =SUM('L. Transmisión'!J7:J48) -> 0 | D9: =C9/B9 -> 0 | E9: =(D9*16.6666%) -> 0
A10: Redes de distribución | B10: 154 | C10: =SUM('Redes de distribución'!J7:J85) -> 0 | D10: =C10/B10 -> 0 | E10: =(D10*16.6666%) -> 0
A11: Comercialización | B11: 48 | C11: =SUM(Comercialización!J8:J34) -> 0 | D11: =C11/B11 -> 0 | E11: =(D11*16.6666%) -> 0
C12: Resultado para cada ítem evaluado | E12: =SUM(E6:E11) -> 0.12094347
E13: Porcentaje total cumplimiento Resol. 5018 de 2019
